rkit/__init__.py
rkit/decorators/__init__.py
rkit/decorators/indexableproperty.py
rkit/patterns/__init__.py
rkit/patterns/observer.py
rkit/patterns/singleton.py
reausokit-0.0.3.dist-info/METADATA
reausokit-0.0.3.dist-info/WHEEL
reausokit-0.0.3.dist-info/licenses/LICENSE
reausokit-0.0.3.dist-info/RECORD
