Metadata-Version: 2.4
Name: ReausoKit
Version: 0.0.3
Summary: Some util functionality for Python Projects.
Project-URL: Homepage, https://github.com/reauso/ReausoKit
Author-email: Rene Ebertowski <r.ebertowski@gmx.de>
License: MIT
License-File: LICENSE
Requires-Python: >=3.11
Requires-Dist: numpy
